allestm/__init__.py
allestm/allestm.py
allestm/parsers.py
allestm/utils.py
allestm/features/__init__.py
allestm/features/base.py
allestm/features/binary.py
allestm/features/categorical.py
allestm/features/continuous.py
allestm/helpers/__init__.py
allestm-1.1.3.dist-info/LICENSE
allestm-1.1.3.dist-info/METADATA
allestm-1.1.3.dist-info/WHEEL
allestm-1.1.3.dist-info/entry_points.txt
allestm-1.1.3.dist-info/top_level.txt
allestm-1.1.3.dist-info/RECORD
